{"latest":1671167926000,"builds":[{"id":1,"success":true,"commit":"2843a9ccbdb3f4fe4a51844290681a5e6cb26308","build_timestamp":1658554149032,"timestamp":1658545200000,"message":"Merge remote-tracking branch 'upstream/crowdin/master'","author":"StarWishsama","target":"Slimefun-2022.07-release.jar"},{"id":2,"success":true,"commit":"5792796ff898309fc6b871f1df18e4f5a00011b3","build_timestamp":1661951885648,"timestamp":1661950645000,"message":":bug: fix(ci): fix missing path","author":"StarWishsama","target":"Slimefun-2022.08-release.jar"},{"id":3,"success":true,"commit":"877a548b2d9ba459f6edffc62f3132feebdcce4a","build_timestamp":1662885962137,"timestamp":1662885198000,"message":":bug: fix(qs): qs version identify shouldn't interrupt startup","author":"StarWishsama","target":"Slimefun-2022.09-release.jar"},{"id":4,"success":true,"commit":"3b9de85c95993ab84c39c20b1166fecb9fa3dd8f","build_timestamp":1671167983935,"timestamp":1671167926000,"message":"Merge branch 'master' into release\n\n# Conflicts:\n#\tsrc/main/java/ren/natsuyuk1/slimefunextra/IntegrationHelper.java","author":"StarWishsama","target":"Slimefun-2022.12-release.jar"}]}