{"latest":1649577986000,"builds":[{"id":1,"success":true,"commit":"996ebdd7af48e8b8eea44ee050210fc4b528f097","build_timestamp":1649214476901,"timestamp":1649207908000,"message":"2.0重制版完成","author":"haiman233","target":"Bump-Build 1 zh-CN(SlimefunGuguProject) (git 996ebdd).jar"},{"id":2,"success":true,"commit":"80ef887cb04c2ca2c1189fddce8d42b96cacbacc","build_timestamp":1649300709247,"timestamp":1649298849000,"message":"Merge pull request #8 from SlimefunGuguProject/dev","author":"ybw0014","target":"Bump-Build 2 zh-CN(SlimefunGuguProject) (git 80ef887).jar"},{"id":3,"success":true,"commit":"9169e59572854428ce47bc26e2afad14ad1427c2","build_timestamp":1649576583189,"timestamp":1649576539000,"message":"修复显示","author":"haiman233","target":"Bump-Build 3 zh-CN(SlimefunGuguProject) (git 9169e59).jar"},{"id":4,"success":true,"commit":"803d02b535b0a11a0fdbe3f19fd25041af4351cf","build_timestamp":1649578133295,"timestamp":1649577986000,"message":"使鉴定系统不再那么鸡肋","author":"haiman233","target":"Bump-Build 4 zh-CN(SlimefunGuguProject) (git 803d02b).jar"}]}