{
    "type": "object",
    "additionalProperties": false,
    "patternProperties": {
        "^[A-Za-z0-9_-]+/[A-Za-z0-9_-]+:[\/A-Za-z0-9_-]+$": {
            "type": "object",
            "required": [
                "options",
                "type"
            ],
            "additionalProperties": false,
            "properties": {
                "type": {
                    "type": "string"
                },
                "options": {
                    "type": "object",
                    "additionalProperties": false,
                    "properties": {
                        "target": {
                            "type": "object",
                            "required": [
                                "name",
                                "version"
                            ],
                            "additionalProperties": false,
                            "properties": {
                                "name": {
                                    "type": "string"
                                },
                                "version": {
                                    "type": "string"
                                }
                            }
                        },
                        "hidden": {
                            "type": "boolean"
                        },
                        "customDir": {
                            "type": "String"
                        }
                    }
                },
                "dependencies": {
                    "type": "object",
                    "additionalProperties": {
                        "type": "object",
                        "additionalProperties": false,
                        "patternProperties": {
                            "^[0-9]+$": {
                                "type": "string"
                            }
                        }
                    }
                }
            }
        }
    }
}
