{"latest":1654357323000,"builds":[{"id":1,"success":true,"commit":"0ec113e6a304412d845dde08aea3974bdf86a72d","build_timestamp":1654153856411,"timestamp":1654145796000,"message":"document update","author":"ljc0424","target":"FinalTech-Build 1 zh-CN(ECRO) (git 0ec113e).jar"},{"id":2,"success":true,"commit":"1b24937f89b8930fcf62fecd652816265b34b342","build_timestamp":1654162263251,"timestamp":1654161836000,"message":"bugfix:\nitem value table: some slimefun item seems cannot not be calculated.","author":"ljc0424","target":"FinalTech-Build 2 zh-CN(ECRO) (git 1b24937).jar"},{"id":3,"success":true,"commit":"d23d7d7a6843e019b8dd35062870f09278bf2678","build_timestamp":1654166086986,"timestamp":1654164768000,"message":"bugfix:\nitem value table: some slimefun item seems cannot not be calculated because of infinity loop.","author":"ljc0424","target":"FinalTech-Build 3 zh-CN(ECRO) (git d23d7d7).jar"},{"id":4,"success":true,"commit":"f4dea16c79304b6e54e5a618d1021c915dce74b7","build_timestamp":1654205722102,"timestamp":1654205102000,"message":"the world will be better🎶","author":"ljc0424","target":"FinalTech-Build 4 zh-CN(ECRO) (git f4dea16).jar"},{"id":5,"success":true,"commit":"efd09465e85668b57f86d083a2e3ba129e603b8b","build_timestamp":1654238041287,"timestamp":1654237528000,"message":"the world will be better🎶","author":"ljc0424","target":"FinalTech-Build 5 zh-CN(ECRO) (git efd0946).jar"},{"id":6,"success":true,"commit":"f6acc55420eeabe468d0ee16b8b1aa3302149f49","build_timestamp":1654252309466,"timestamp":1654251065000,"message":"the world will be better🎶","author":"ljc0424","target":"FinalTech-Build 6 zh-CN(ECRO) (git f6acc55).jar"},{"id":7,"success":true,"commit":"2a7c1b6d4f26e0be849f703f504bdb8d91f2ffaf","build_timestamp":1654257156524,"timestamp":1654256736000,"message":"bugfix:\nitem value table: infinity value output item should not be output.","author":"ljc0424","target":"FinalTech-Build 7 zh-CN(ECRO) (git 2a7c1b6).jar"},{"id":8,"success":true,"commit":"87bfa6052958c289015a46b414bdca0c6a687d7f","build_timestamp":1654357519088,"timestamp":1654357323000,"message":"small info fix.","author":"ljc0424","target":"FinalTech-Build 8 zh-CN(ECRO) (git 87bfa60).jar"}]}